acli/__init__.py
acli/config.py
acli/connections.py
acli/constants.py
acli/ec2.py
acli/errors.py
acli/output.py
acli/utils.py
acli/commands/__init__.py
acli/commands/account.py
acli/commands/ami.py
acli/commands/asg.py
acli/commands/clean.py
acli/commands/ec2.py
acli/commands/efs.py
acli/commands/eip.py
acli/commands/elb.py
acli/commands/es.py
acli/commands/lc.py
acli/commands/route53.py
acli/commands/s3.py
acli/commands/secgroup.py
acli/commands/vpc.py
acli/output/__init__.py
acli/output/account.py
acli/output/asg.py
acli/output/cloudwatch.py
acli/output/ec2.py
acli/output/efs.py
acli/output/eip.py
acli/output/elb.py
acli/output/es.py
acli/output/route53.py
acli/output/s3.py
acli/output/secgroup.py
acli/output/snapshots.py
acli/output/vpc.py
acli/services/__init__.py
acli/services/account.py
acli/services/asg.py
acli/services/clean.py
acli/services/cloudwatch.py
acli/services/ec2.py
acli/services/efs.py
acli/services/eip.py
acli/services/elb.py
acli/services/es.py
acli/services/route53.py
acli/services/s3.py
acli/services/secgroup.py
acli/services/vpc.py
acli-0.1.27.data/scripts/acli
acli-0.1.27.dist-info/DESCRIPTION.rst
acli-0.1.27.dist-info/METADATA
acli-0.1.27.dist-info/RECORD
acli-0.1.27.dist-info/WHEEL
acli-0.1.27.dist-info/metadata.json
acli-0.1.27.dist-info/pbr.json
acli-0.1.27.dist-info/top_level.txt
