Metadata-Version: 2.0
Name: acli
Version: 0.1.27
Summary: A CLI to manage AWS resources
Home-page: http://github.com/jonhadfield/acli
Author: Jon Hadfield
Author-email: jon@lessknown.co.uk
License: MIT
Download-URL: https://github.com/jonhadfield/acli/tarball/0.1.27
Keywords: aws,Python,cli,amazon,ec2
Platform: any
Classifier: Programming Language :: Python
Classifier: Development Status :: 3 - Alpha
Classifier: Natural Language :: English
Classifier: Environment :: Console
Classifier: Intended Audience :: System Administrators
Classifier: Intended Audience :: Developers
Classifier: License :: OSI Approved :: MIT License
Classifier: Operating System :: OS Independent
Classifier: Topic :: System :: Networking
Requires-Dist: boto3 (>=1.3.1)
Requires-Dist: botocore (>=1.4.39)
Requires-Dist: colorclass (>=2.2.0)
Requires-Dist: docopt (>=0.6.2)
Requires-Dist: humanize (>=0.5.1)
Requires-Dist: requests (>=2.10.0)
Requires-Dist: terminaltables (>=3.0.0)
